coincidencetest/__init__.py
coincidencetest/_coincidencetest.py
coincidencetest/fca.py
coincidencetest/log_formats.py
coincidencetest/version.txt
coincidencetest-1.0.31.data/scripts/coincidence-clustering
coincidencetest-1.0.31.data/scripts/coincidencetest-distribution-plot
coincidencetest-1.0.31.data/scripts/coincidencetest-plot
coincidencetest-1.0.31.dist-info/METADATA
coincidencetest-1.0.31.dist-info/WHEEL
coincidencetest-1.0.31.dist-info/top_level.txt
coincidencetest-1.0.31.dist-info/RECORD
