Metadata-Version: 2.1
Name: coincidencetest
Version: 1.0.31
Summary: An exact test for coincidence of feature values along a sample set.
Home-page: https://github.com/nadeemlab/coincidencetest
Author: James Mathews
Author-email: mathewj2@mskcc.org
Project-URL: Documentation, https://github.com/nadeemlab/coincidencetest
Project-URL: Source code, https://github.com/nadeemlab/coincidencetest
Classifier: Programming Language :: Python :: 3
Classifier: Topic :: Scientific/Engineering
Classifier: Intended Audience :: Science/Research
Requires-Python: >=3.8
Requires-Dist: pandas (==1.3.2)
Requires-Dist: python-igraph (==0.9.6)
